{
    "version": "1.5.5",
    "description": "A Cataclysm: Dark Days Ahead launcher with additional features",
    "license": "MIT",
    "homepage": "https://github.com/remyroy/CDDA-Game-Launcher",
    "architecture": {
        "64bit": {
            "url": "https://github.com/remyroy/CDDA-Game-Launcher/releases/download/v1.5.5/cddagl_installer_v1.5.5.exe",
            "hash": "146fd5e610007d143c5e503a5e8b941a1e74c1d258545d8867dd66fd72c5c5d4"
        }
    },
    "innosetup": true,
    "shortcuts": [
        [
            "launcher.exe",
            "CDDA Game Launcher"
        ]
    ],
    "persist": "cdda",
    "checkver": "github",
    "autoupdate": {
        "architecture": {
            "64bit": {
                "url": "https://github.com/remyroy/CDDA-Game-Launcher/releases/download/v$version/cddagl_installer_v$version.exe"
            }
        }
    }
}
